onenonly/__init__.py
onenonly/LinkedList/__init__.py
onenonly/List/__init__.py
onenonly/areas/__init__.py
onenonly/array/__init__.py
onenonly/binary/__init__.py
onenonly/complex/__init__.py
onenonly/const/__init__.py
onenonly/data_toolkit/__init__.py
onenonly/data_toolkit/utils.py
onenonly/learn/__init__.py
onenonly/learn/preprocessing/__init__.py
onenonly/maths/__init__.py
onenonly/matrix/__init__.py
onenonly/number/__init__.py
onenonly/perimeter/__init__.py
onenonly/periodic_table/__init__.py
onenonly/physics/__init__.py
onenonly/physics/simulation.py
onenonly/queue/__init__.py
onenonly/search/__init__.py
onenonly/sort/__init__.py
onenonly/stack/__init__.py
onenonly/stats/__init__.py
onenonly/units/__init__.py
onenonly/units/length/__init__.py
onenonly/units/magnetic/__init__.py
onenonly/units/pressure/__init__.py
onenonly/units/temperature/__init__.py
onenonly/units/weight/__init__.py
onenonly/utils/__init__.py
onenonly/vector/__init__.py
onenonly-0.5.1.dist-info/LICENSE
onenonly-0.5.1.dist-info/METADATA
onenonly-0.5.1.dist-info/WHEEL
onenonly-0.5.1.dist-info/top_level.txt
onenonly-0.5.1.dist-info/RECORD
