Metadata-Version: 2.1
Name: onenonly
Version: 0.5.1
Summary: A python library
Home-page: https://github.com/Sahil-Rajwar-2004/One-n-Only
Author: Sahil Rajwar
Project-URL: Source, https://github.com/Sahil-Rajwar-2004/One-n-Only
Project-URL: Bug Reports, https://github.com/Sahil-Rajwar-2004/One-n-Only/issues
Keywords: math library numpy-alternative sci-calc calc
Classifier: Development Status :: 5 - Production/Stable
Classifier: License :: OSI Approved :: MIT License
Classifier: Programming Language :: Python :: 3
Classifier: Programming Language :: Python :: 3.8
Classifier: Programming Language :: Python :: 3.9
Classifier: Programming Language :: Python :: 3.10
Classifier: Programming Language :: Python :: 3.11
License-File: LICENSE
Requires-Dist: numpy
Requires-Dist: pandas
Requires-Dist: scipy
Requires-Dist: matplotlib
